[
  {
    "text": "@JordanImran2 @PieDAO_DeFi Dayum, that APY is nuts! That said I am getting 120% APY on my stake in $PLAY- $DOUGH LP, so I'm not surprised. Put in 2K, getting 3.2K rewards per year. Very underrated project given it gives exposure to all the best #Metaverse and #blockchaingaming projects.",
    "id": "1484209565600296960",
    "created_at": "2022-01-20T17:01:50.000Z",
    "author_id": "261333504",
    "author": {
      "username": "TheAxiePack",
      "id": "261333504",
      "name": "Gank: $FTM 👻 $ONE",
      "profile_image_url": "https://pbs.twimg.com/profile_images/1520415635565694976/Sqhz_ugS_normal.jpg"
    }
  },
  {
    "text": "The metaverse trend = unstoppable\n\nMetaverse NFT Index $PLAY \n\n@PieDAO_DeFi",
    "id": "1463894914132029455",
    "created_at": "2021-11-25T15:38:40.000Z",
    "author_id": "1301583995793215489",
    "author": {
      "profile_image_url": "https://pbs.twimg.com/profile_images/1505579063401984006/yJsk7-Mt_normal.jpg",
      "id": "1301583995793215489",
      "name": "rdraper.eth",
      "username": "DickieDraper"
    }
  },
  {
    "text": "Metaverse NFT Index $PLAY : \n\nThe metaverse / P2E trend seems unstoppable, the $PLAY index by @PieDAO_DeFi shows how fast the sector is growing https://t.co/j3zszNLGp7",
    "id": "1463871447097557006",
    "created_at": "2021-11-25T14:05:25.000Z",
    "author_id": "867033020338810880",
    "author": {
      "name": "Elkmar",
      "id": "867033020338810880",
      "profile_image_url": "https://pbs.twimg.com/profile_images/1488838515844595712/naxsRjpb_normal.png",
      "username": "cryptelkmar"
    }
  },
  {
    "text": "Long $PLAY from @PieDAO_DeFi \nThx to @AxieInfinity staking #NFT option, yes staking #AXS 🔥\n\nSoon there will be some $AXS millionaires in Vietnam 🇻🇳 ;) https://t.co/stVuMogAtt",
    "id": "1443996166853697537",
    "created_at": "2021-10-01T17:48:08.000Z",
    "author_id": "420490529",
    "author": {
      "profile_image_url": "https://pbs.twimg.com/profile_images/1375008408122851331/LMC3gWcR_normal.jpg",
      "username": "Loedere",
      "name": "LOΞDΞRΞ - 🦇🔊",
      "id": "420490529"
    }
  },
  {
    "text": "Do you know you can get the exposure to:\n\n👉 8-10 Largecap #cryptocurrency at the same time \n👉Metaverse NFT Index through Play \n👉$BTC, $ETH, Defi+L, Defi+S \n\nyou just need to buy Defi+L, PLAY and BCP at @PieDAO_DeFi \n\n#Indiawantscrypto #indialearnscrypto #way2wealth",
    "id": "1479422039836409856",
    "created_at": "2022-01-07T11:57:55.000Z",
    "author_id": "1287096195727282176",
    "author": {
      "profile_image_url": "https://pbs.twimg.com/profile_images/1487804811873767424/qJ59YiRG_normal.jpg",
      "id": "1287096195727282176",
      "username": "1way2wealth",
      "name": "way2wealth"
    }
  },

  {
    "text": "@MiddleChildPabk $PLAY @PieDAO_DeFi has a metaverse index similar to $MVI.  $3.7m MC, curated by a solid team.  With the rise of #Metaverse cryptos it's only a matter of time before people catch on to it.",
    "id": "1455005260767023108",
    "created_at": "2021-11-01T02:54:21.000Z",
    "author_id": "2486964988",
    "author": {
      "profile_image_url": "https://pbs.twimg.com/profile_images/1510620602750717952/PKNGWtdF_normal.jpg",
      "username": "OnlineResell",
      "name": "GRIMACE",
      "id": "2486964988"
    }
  },
  {
    "text": "@Ubah01 @TeddyCleps No it doesn't. Check out $PLAY token basket via @PieDAO_DeFi ... I put in $200 in April it's worth ~900? $1300 during the big pump earlier in the year...",
    "id": "1474191848386269184",
    "created_at": "2021-12-24T01:35:00.000Z",
    "author_id": "1373885412905730049",
    "author": {
      "profile_image_url": "https://pbs.twimg.com/profile_images/1507171579582726147/Zly5VGIA_normal.png",
      "id": "1373885412905730049",
      "username": "SaintlyNFT",
      "name": "upnorth.eth"
    }
  },
  {
    "text": "@blknoiz06 i've been telling people to buy the $PLAY NFT/metaverse index through @PieDAO_DeFi for months and months.\n\nmy work is unappreciated.",
    "id": "1461440377290952711",
    "created_at": "2021-11-18T21:05:12.000Z",
    "author_id": "767131040146227200",
    "author": {
      "username": "ThinkingLSD",
      "id": "767131040146227200",
      "name": "jerry (🦆,🦆)",
      "profile_image_url": "https://pbs.twimg.com/profile_images/1480810607280627712/vYSWX4uW_normal.jpg"
    }
  }
]
